noless/__init__.py
noless/agents.py
noless/art.py
noless/autopilot.py
noless/cli.py
noless/cli_interactive.py
noless/code_validator.py
noless/feedback_loop.py
noless/generator.py
noless/local_models.py
noless/ollama_client.py
noless/openml_search.py
noless/project_stats.py
noless/query_understanding.py
noless/refinement.py
noless/search.py
noless/startup.py
noless/templates.py
noless/ui.py
noless/utils.py
noless-0.1.1a0.dist-info/licenses/LICENSE
noless-0.1.1a0.dist-info/METADATA
noless-0.1.1a0.dist-info/WHEEL
noless-0.1.1a0.dist-info/entry_points.txt
noless-0.1.1a0.dist-info/top_level.txt
noless-0.1.1a0.dist-info/RECORD
