Metadata-Version: 2.4
Name: noless
Version: 0.1.1a0
Summary: Multi-agent CLI for automatic dataset discovery and ML project generation
Home-page: https://github.com/DWE-CLOUD/NoLess
Author: NoLess Team
License: MIT
Project-URL: Source, https://github.com/DWE-CLOUD/NoLess
Project-URL: Issues, https://github.com/DWE-CLOUD/NoLess/issues
Project-URL: Documentation, https://github.com/DWE-CLOUD/NoLess#readme
Keywords: cli ai machine-learning autopilot multi-agent
Classifier: Development Status :: 3 - Alpha
Classifier: Intended Audience :: Developers
Classifier: Topic :: Scientific/Engineering :: Artificial Intelligence
Classifier: License :: OSI Approved :: MIT License
Classifier: Operating System :: OS Independent
Classifier: Programming Language :: Python :: 3
Classifier: Programming Language :: Python :: 3.8
Classifier: Programming Language :: Python :: 3.9
Classifier: Programming Language :: Python :: 3.10
Classifier: Programming Language :: Python :: 3.11
Requires-Python: >=3.8
License-File: LICENSE
Requires-Dist: click>=8.1.0
Requires-Dist: requests>=2.31.0
Requires-Dist: beautifulsoup4>=4.12.0
Requires-Dist: rich>=13.0.0
Requires-Dist: huggingface-hub>=0.19.0
Requires-Dist: kaggle>=1.5.16
Requires-Dist: torch>=2.0.0
Requires-Dist: tensorflow>=2.13.0
Requires-Dist: scikit-learn>=1.3.0
Requires-Dist: pandas>=2.0.0
Requires-Dist: numpy>=1.24.0
Requires-Dist: pyyaml>=6.0
Requires-Dist: jinja2>=3.1.0
Requires-Dist: openml>=0.14.0
Requires-Dist: anthropic>=0.39.0
Requires-Dist: openai>=1.0.0
Requires-Dist: questionary>=2.0.0
Requires-Dist: prompt_toolkit>=3.0.0
Requires-Dist: colorama>=0.4.6
Requires-Dist: pyfiglet>=1.0.0
Dynamic: author
Dynamic: classifier
Dynamic: description
Dynamic: description-content-type
Dynamic: home-page
Dynamic: keywords
Dynamic: license
Dynamic: license-file
Dynamic: project-url
Dynamic: requires-dist
Dynamic: requires-python
Dynamic: summary
